lib/__init__.py
lib/middleware.py
lib/path.py
lib/request.py
lib/response.py
lib/router.py
lib/session.py
lib/utils.py
wsgitoolbox-0.0.2.dist-info/METADATA
wsgitoolbox-0.0.2.dist-info/WHEEL
wsgitoolbox-0.0.2.dist-info/top_level.txt
wsgitoolbox-0.0.2.dist-info/RECORD
