Metadata-Version: 2.1
Name: wsgitoolbox
Version: 0.0.2
Summary: Toolbox for python web development
Home-page: UNKNOWN
Author: Hakim Rachidi
Author-email: hakimrachidi02@gmail.com
License: UNKNOWN
Platform: UNKNOWN
Requires-Dist: werkzeug (>=0.16.0)
